yayy/__init__.py
yayy/constants.py
yayy/main.py
yayy/utils.py
yayy/assets/data.json
yayy-0.1.3.dist-info/METADATA
yayy-0.1.3.dist-info/WHEEL
yayy-0.1.3.dist-info/entry_points.txt
yayy-0.1.3.dist-info/top_level.txt
yayy-0.1.3.dist-info/RECORD
